setup.py
tankard/__init__.py
tankard/converters.py
tankard/debug.py
tankard.egg-info/PKG-INFO
tankard.egg-info/SOURCES.txt
tankard.egg-info/dependency_links.txt
tankard.egg-info/requires.txt
tankard.egg-info/top_level.txt