Metadata-Version: 1.1
Name: tankard
Version: 0.0.2
Summary: tankard
Home-page: https://github.com/lgastako/tankard
Author: John Evans
Author-email: lgastako@gmail.com
License: UNKNOWN
Platform: UNKNOWN
Provides: tankard
